clinicaltrialsconnect/__init__.py
clinicaltrialsconnect/start.py
clinicaltrialsconnect-0.0.0.dist-info/entry_points.txt
clinicaltrialsconnect-0.0.0.dist-info/LICENSE
clinicaltrialsconnect-0.0.0.dist-info/METADATA
clinicaltrialsconnect-0.0.0.dist-info/WHEEL
clinicaltrialsconnect-0.0.0.dist-info/RECORD
